neuropower
