Metadata-Version: 1.1
Name: neuropower
Version: 0.2.8
Summary: A package to perform power analyses for neuroimaging data
Home-page: https://github.com/neuropower/neuropower-core
Author: Joke Durnez
Author-email: joke.durnez@gmail.com
License: MIT
Keywords: statistics power fmri neuroimaging inference samplesize
Platform: UNKNOWN
Classifier: Development Status :: 4 - Beta
Classifier: License :: OSI Approved :: MIT License
Classifier: Programming Language :: Python :: 2.7
